bigeye_sdk/__init__.py
bigeye_sdk/__version__.py
bigeye_sdk/authentication/__init__.py
bigeye_sdk/authentication/api_authentication.py
bigeye_sdk/authentication/config.py
bigeye_sdk/authentication/credentials.py
bigeye_sdk/authentication/enums.py
bigeye_sdk/bigconfig_validation/__init__.py
bigeye_sdk/bigconfig_validation/big_config_reports.py
bigeye_sdk/bigconfig_validation/validation_context.py
bigeye_sdk/bigconfig_validation/validation_functions.py
bigeye_sdk/bigconfig_validation/validation_models.py
bigeye_sdk/bigconfig_validation/yaml_model_base.py
bigeye_sdk/bigconfig_validation/yaml_validation_error_messages.py
bigeye_sdk/class_ext/__init__.py
bigeye_sdk/class_ext/dataclass_ext.py
bigeye_sdk/class_ext/enum_ext.py
bigeye_sdk/client/__init__.py
bigeye_sdk/client/base_client.py
bigeye_sdk/client/datawatch_client.py
bigeye_sdk/client/enum.py
bigeye_sdk/client/generated_datawatch_client.py
bigeye_sdk/controller/__init__.py
bigeye_sdk/controller/custom_repository_controller.py
bigeye_sdk/controller/delta_controller.py
bigeye_sdk/controller/lineage_controller.py
bigeye_sdk/controller/metric_controller.py
bigeye_sdk/controller/metric_suite_controller.py
bigeye_sdk/decorators/__init__.py
bigeye_sdk/decorators/dataclass_decorators.py
bigeye_sdk/exceptions/__init__.py
bigeye_sdk/exceptions/exceptions.py
bigeye_sdk/functions/__init__.py
bigeye_sdk/functions/athena.py
bigeye_sdk/functions/aws.py
bigeye_sdk/functions/bigconfig_functions.py
bigeye_sdk/functions/casing.py
bigeye_sdk/functions/core_py_functs.py
bigeye_sdk/functions/dbt.py
bigeye_sdk/functions/delta_functions.py
bigeye_sdk/functions/file_functs.py
bigeye_sdk/functions/helpers.py
bigeye_sdk/functions/issue_functions.py
bigeye_sdk/functions/metric_functions.py
bigeye_sdk/functions/metric_run_functions.py
bigeye_sdk/functions/notifications.py
bigeye_sdk/functions/s3.py
bigeye_sdk/functions/schema_change_functions.py
bigeye_sdk/functions/schema_functions.py
bigeye_sdk/functions/search_and_match_functions.py
bigeye_sdk-0.8.5.dist-info/LICENSE
bigeye_sdk-0.8.5.dist-info/METADATA
bigeye_sdk-0.8.5.dist-info/WHEEL
bigeye_sdk-0.8.5.dist-info/RECORD
